[
 {
  "pk": 3, 
  "model": "server.sipprofile", 
  "fields": {
   "domain": "", 
   "no_view_param": "    <!--<param name=\"codec-prefs\" value=\"{{ sofia.codec_prefs }}\"/>-->\r\n    <!--<param name=\"use-rtp-timer\" value=\"true\"/> OLD -->\r\n   \r\n\r\n <!-- When calls are in no media this will bring them back to media \twhen you press the hold button.    -->\r\n    <!--<param name=\"media-option\" value=\"resume-media-on-hold\"/> -->\r\n    <!-- This will allow a call after an attended transfer go back to \t bypass media after an attended transfer.    -->\r\n    <!--<param name=\"media-option\" value=\"bypass-media-after-att-xfer\"/>-->\r\n    <!-- <param name=\"user-agent-string\" value=\"FreeSWITCH Rocks!\"/> -->\r\n<!-- If you want FreeSWITCH to shutdown if this profile fails to load, uncomment the next line. -->\r\n\t<!-- <param name=\"shutdown-on-fail\" value=\"true\"/> -->\r\n<!--<param name=\"apply-nat-acl\" value=\"nat.auto\"/> ???? -->\r\n    <!--<param name=\"aggressive-nat-detection\" value=\"true\"/>-->\r\n    <!--\r\n\tThere are known issues (asserts and segfaults) when 100rel is enabled.\r\n\tIt is not recommended to enable 100rel at this time.\r\n    -->\r\n    <!--<param name=\"enable-100rel\" value=\"true\"/>-->\r\n    <!-- Enable Compact SIP headers. -->\r\n    <!--<param name=\"enable-compact-headers\" value=\"true\"/>-->\r\n    <!--\r\n\tenable/disable session timers \r\n    -->\r\n    <!--<param name=\"enable-timer\" value=\"false\"/>-->\r\n    <!--<param name=\"minimum-session-expires\" value=\"120\"/>-->\r\n    <!--<param name=\"apply-inbound-acl\" value=\"domains\"/> UNCOMENT -->\r\n    <!--\r\n\tThis defines your local network, by default we detect your local network\r\n\tand create this localnet.auto ACL for this.\r\n    -->\r\n    <!--<param name=\"apply-register-acl\" value=\"domains\"/>-->\r\n    <!--<param name=\"dtmf-type\" value=\"info\"/>-->\r\n    <!--<param name=\"manage-shared-appearance\" value=\"true\"/>-->\r\n    <!-- used to share presence info across sofia profiles -->\r\n    <!-- Name of the db to use for this profile -->\r\n    <!--<param name=\"dbname\" value=\"share_presence\"/>-->\r\n    <!--<param name=\"presence-hosts\" value=\"$${domain}\"/>-->\r\n    <!-- ************************************************* -->\r\n    \r\n    <!-- This setting is for AAL2 bitpacking on G726 -->\r\n    <!-- <param name=\"bitpacking\" value=\"aal2\"/> -->\r\n    <!--max number of open dialogs in proceeding -->\r\n    <!--<param name=\"max-proceeding\" value=\"1000\"/>-->\r\n    <!--session timers for all call to expire after the specified seconds -->\r\n    <!--<param name=\"session-timeout\" value=\"120\"/>-->\r\n    <!-- Can be 'true' or 'contact' -->\r\n    <!--<param name=\"multiple-registrations\" value=\"contact\"/>-->\r\n      <!-- if you want to send any special bind params of your own -->\r\n    <!--<param name=\"bind-params\" value=\"transport=udp\"/>-->\r\n    <!--<param name=\"unregister-on-options-fail\" value=\"true\"/>-->\r\n    <!-- turn on auto-flush during bridge (skip timer sleep when the socket already has data) \r\n\t (reduces delay on latent connections default true, must be disabled explicitly)-->\r\n    <!--<param name=\"rtp-autoflush-during-bridge\" value=\"false\"/>-->\r\n    \r\n    <!--If you don't want to pass through timestamps from 1 RTP call to another (on a per call basis with rtp_rewrite_timestamps chanvar)-->\r\n    <!--<param name=\"rtp-rewrite-timestamps\" value=\"true\"/>-->\r\n    <!--<param name=\"pass-rfc2833\" value=\"true\"/>-->\r\n    <!--Uncomment to set all inbound calls to no media mode-->\r\n    <!--<param name=\"inbound-bypass-media\" value=\"true\"/>-->\r\n\r\n    <!--Uncomment to let calls hit the dialplan *before* you decide if the codec is ok-->\r\n    <!--<param name=\"inbound-late-negotiation\" value=\"true\"/>-->\r\n    \r\n \r\n    <!-- accept any authentication without actually checking (not a good feature for most people) -->\r\n    <!-- <param name=\"accept-blind-auth\" value=\"true\"/> -->\r\n    \r\n    <!-- suppress CNG on this profile or per call with the 'suppress_cng' variable -->\r\n    <!-- <param name=\"suppress-cng\" value=\"true\"/> -->\r\n        <!--Uncomment if you want to force the outbound leg of a bridge to only offer the codec \r\n\tthat the originator is using-->\r\n    <!--<param name=\"disable-transcoding\" value=\"true\"/>-->\r\n    <!-- Handle 302 Redirect in the dialplan -->\r\n    <!--<param name=\"manual-redirect\" value=\"true\"/> -->\r\n    <!-- Disable Transfer -->\r\n    <!--<param name=\"disable-transfer\" value=\"true\"/> -->\r\n    <!-- Disable Register -->\r\n    <!--<param name=\"disable-register\" value=\"true\"/> -->\r\n    <!-- Used for when phones respond to a challenged ACK with method INVITE in the hash -->\r\n    <!--<param name=\"NDLB-broken-auth-hash\" value=\"true\"/>-->\r\n    <!-- add a ;received=\"<ip>:<port>\" to the contact when replying to register for nat handling -->\r\n    <!--<param name=\"NDLB-received-in-nat-reg-contact\" value=\"true\"/>-->\r\n<!-- VAD choose one (out is a good choice); -->\r\n    <!-- <param name=\"vad\" value=\"in\"/> -->\r\n    <!-- <param name=\"vad\" value=\"out\"/> -->\r\n    <!-- <param name=\"vad\" value=\"both\"/> -->\r\n    <!--<param name=\"alias\" value=\"sip:10.0.1.251:5555\"/>-->\r\n    <!--force suscription expires to a lower value than requested-->\r\n    <!--<param name=\"force-subscription-expires\" value=\"60\"/>-->\r\n    <!-- disable register and transfer which may be undesirable in a public switch -->\r\n    <!--<param name=\"disable-transfer\" value=\"true\"/>-->\r\n    <!--<param name=\"disable-register\" value=\"true\"/>-->\r\n\r\n    <!-- \r\n\t enable-3pcc can be set to either 'true' or 'proxy', true accepts the call\r\n\t right away, proxy waits until the call has been answered then sends accepts\r\n    -->\r\n    <!--<param name=\"enable-3pcc\" value=\"true\"/>-->\r\n\t\r\n    <!-- use at your own risk or if you know what this does.-->\r\n    <!--<param name=\"NDLB-force-rport\" value=\"true\"/>-->\r\n    <!--\r\n\tChoose the realm challenge key. Default is auto_to if not set. \r\n\t\r\n\tauto_from  - uses the from field as the value for the sip realm.\r\n\tauto_to    - uses the to field as the value for the sip realm.\r\n\t<anyvalue> - you can input any value to use for the sip realm.\r\n\r\n\tIf you want URL dialing to work you'll want to set this to auto_from.\r\n\t\r\n\tIf you use any other value besides auto_to or auto_from you'll loose\r\n\tthe ability to do multiple domains.\r\n\t\r\n\tNote: comment out to restore the behavior before 2008-09-29\r\n\r\n    --> \r\n<!--<param name=\"disable-rtp-auto-adjust\" value=\"true\"/>-->\r\n    <!-- on inbound calls make the uuid of the session equal to the sip call id of that call -->\r\n    <!--<param name=\"inbound-use-callid-as-uuid\" value=\"true\"/>-->\r\n    <!-- on outbound calls set the callid to match the uuid of the session -->\r\n    <!--<param name=\"outbound-use-uuid-as-callid\" value=\"true\"/>-->\r\n    <!-- set to false disable this feature -->\r\n    <!--<param name=\"rtp-autofix-timing\" value=\"false\"/>-->\r\n\r\n    <!-- set this param to false if your gateway for some reason hates X- headers that it is supposed to ignore-->\r\n    <!--<param name=\"pass-callee-id\" value=\"false\"/>-->\r\n\r\n    <!-- clear clears them all or supply the name to add or the name prefixed with ~ to remove\r\n\t valid values:\r\n\r\n\t clear\r\n\t CISCO_SKIP_MARK_BIT_2833\r\n\t SONUS_SEND_INVALID_TIMESTAMP_2833\r\n\r\n    -->\r\n    <!--<param name=\"auto-rtp-bugs\" data=\"clear\"/>-->\r\n\r\n\t <!-- the following can be used as workaround with bogus SRV/NAPTR records -->\r\n\t <!--<param name=\"disable-srv\" value=\"false\" />-->\r\n\t <!--<param name=\"disable-naptr\" value=\"false\" />-->\r\n\r\n\t<!-- The following can be used to fine-tune timers within sofia's transport layer \r\n\t\t Those settings are for advanced users and can safely be left as-is -->\r\n\t\t\r\n\t<!-- Initial retransmission interval (in milliseconds).\r\n\t\tSet the T1 retransmission interval used by the SIP transaction engine. \r\n\t\tThe T1 is the initial duration used by request retransmission timers A and E (UDP) as well as response retransmission timer G. \t -->\r\n\t<!-- <param name=\"timer-T1\" value=\"500\" /> -->\r\n\t\r\n\t<!--  Transaction timeout (defaults to T1 * 64).\r\n\t\tSet the T1x64 timeout value used by the SIP transaction engine.\r\n\t\tThe T1x64 is duration used for timers B, F, H, and J (UDP) by the SIP transaction engine. \r\n\t\tThe timeout value T1x64 can be adjusted separately from the initial retransmission interval T1. -->\r\n\t<!-- <param name=\"timer-T1X64\" value=\"32000\" /> -->\r\n\t\r\n\t\r\n\t<!-- Maximum retransmission interval (in milliseconds).\r\n\t\tSet the maximum retransmission interval used by the SIP transaction engine. \r\n\t\tThe T2 is the maximum duration used for the timers E (UDP) and G by the SIP transaction engine. \r\n\t\tNote that the timer A is not capped by T2. Retransmission interval of INVITE requests grows exponentially \r\n\t\tuntil the timer B fires.  -->\r\n\t<!-- <param name=\"timer-T2\" value=\"4000\" /> -->\r\n\t\t\r\n\t<!--\r\n\t\tTransaction lifetime (in milliseconds).\r\n\t\tSet the lifetime for completed transactions used by the SIP transaction engine. \r\n\t\tA completed transaction is kept around for the duration of T4 in order to catch late responses. \r\n\t\tThe T4 is the maximum duration for the messages to stay in the network and the duration of SIP timer K. -->\r\n\t<!-- <param name=\"timer-T4\" value=\"4000\" /> -->\r\n", 
   "name": "internal", 
   "other_param": "<param name=\"log-auth-failures\" value=\"true\"/>\r\n<param name=\"rfc2833-pt\" value=\"101\"/>\r\n<param name=\"dialplan\" value=\"XML\"/>\r\n    <param name=\"dtmf-duration\" value=\"100\"/>\r\n<param name=\"local-network-acl\" value=\"localnet.auto\"/>\r\n    <param name=\"record-path\" value=\"$${base_dir}/recordings\"/>\r\n    <param name=\"record-template\" value=\"${caller_id_number}.${target_domain}.${strftime(%Y-%m-%d-%H-%M-%S)}.wav\"/>\r\n    <!--enable to use presence -->\r\n    <param name=\"manage-presence\" value=\"true\"/>\r\n  <!--set to 'greedy' if you want your codec list to take precedence -->\r\n    <param name=\"inbound-codec-negotiation\" value=\"generous\"/>\r\n<param name=\"hold-music\" value=\"$${hold_music}\"/>\r\n    \t\r\n<param name=\"rtp-timer-name\" value=\"soft\"/>\r\n\r\n    <!-- TLS: disabled by default, set to \"true\" to enable -->\r\n    <param name=\"tls\" value=\"$${internal_ssl_enable}\"/>\r\n    <!-- additional bind parameters for TLS -->\r\n    <param name=\"tls-bind-params\" value=\"transport=tls\"/>\r\n    <!-- Port to listen on for TLS requests. (5061 will be used if unspecified) -->\r\n    <param name=\"tls-sip-port\" value=\"$${internal_tls_port}\"/>\r\n    <!-- Location of the agent.pem and cafile.pem ssl certificates (needed for TLS server) -->\r\n    <param name=\"tls-cert-dir\" value=\"$${internal_ssl_dir}\"/>\r\n    <!-- TLS version (\"sslv23\" (default), \"tlsv1\"). NOTE: Phones may not work with TLSv1 -->\r\n    <param name=\"tls-version\" value=\"$${sip_tls_version}\"/>\r\n<!--TTL for nonce in sip auth-->\r\n    <param name=\"nonce-ttl\" value=\"60\"/>\r\n    <param name=\"auth-calls\" value=\"$${internal_auth_calls}\"/>\r\n    <!-- Force the user and auth-user to match. -->\r\n    <param name=\"inbound-reg-force-matching-username\" value=\"true\"/>\r\n    <!-- on authed calls, authenticate *all* the packets not just invite -->\r\n    <param name=\"auth-all-packets\" value=\"false\"/>\r\n    <!-- rtp inactivity timeout -->\r\n    <param name=\"rtp-timeout-sec\" value=\"300\"/>\r\n    <param name=\"rtp-hold-timeout-sec\" value=\"1800\"/>\r\n    <!--\r\n\tThese are enabled to make the default config work better out of the box.\r\n\tIf you need more than ONE domain you'll need to not use these options.\r\n\r\n    -->\r\n    <!--all inbound reg will look in this domain for the users -->\r\n    <param name=\"force-register-domain\" value=\"$${domain}\"/>\r\n    <!--force the domain in subscriptions to this value -->\r\n    <param name=\"force-subscription-domain\" value=\"$${domain}\"/>\r\n    <!--all inbound reg will stored in the db using this domain -->\r\n    <param name=\"force-register-db-domain\" value=\"$${domain}\"/>\r\n    <param name=\"challenge-realm\" value=\"auto_from\"/>      \r\n\t", 
   "enabled": true, 
   "sip_ip": "192.168.51.100", 
   "ext_rtp_ip": "", 
   "sip_port": 5040, 
   "comments": "", 
   "server": 2, 
   "alias": [
    2
   ], 
   "proxy_media": true, 
   "accept_blind_reg": false, 
   "gateway": [
    1
   ], 
   "context": 2, 
   "outbound_codec_prefs": "G729,PCMU,GSM", 
   "rtp_ip": "192.168.51.100", 
   "ext_sip_ip": "", 
   "codec_prefs": "G729,GSM,PCMU"
  }
 }
]
